textual_ascii_image_magicmaana/src/__init__.py
textual_ascii_image_magicmaana/src/ascii_image.py
textual_ascii_image_magicmaana-0.0.1.dist-info/licenses/LICENSE
textual_ascii_image_magicmaana-0.0.1.dist-info/METADATA
textual_ascii_image_magicmaana-0.0.1.dist-info/WHEEL
textual_ascii_image_magicmaana-0.0.1.dist-info/top_level.txt
textual_ascii_image_magicmaana-0.0.1.dist-info/RECORD
