Metadata-Version: 2.4
Name: textual_ascii_image_magicmaana
Version: 0.0.1
Summary: A small, single file, package to convert a PIL image into a Rich / Textual compatible ascii image.
Author-email: Theo <theobaker99@gmail.com>
License-Expression: MIT
Project-URL: Homepage, https://github.com/pypa/sampleproject
Project-URL: Issues, https://github.com/pypa/sampleproject/issues
Classifier: Programming Language :: Python :: 3
Classifier: Operating System :: OS Independent
Requires-Python: >=3.9
License-File: LICENSE
Dynamic: license-file
